{"book":"Psalm","chapter":21,"verses":[{"text":["For the music director. A Psalm of David."]},{"verse":1,"text":["> Lord, the king will rejoice in Your strength,","> And how greatly he will rejoice in Your salvation!"]},{"text":["---"]},{"verse":2,"text":["> You have granted him his heart’s desire,","> And You have not denied the request of his lips.","> Selah"]},{"verse":3,"text":["> For You welcome him with the blessings of good things;","> You place a crown of pure gold upon his head."]},{"verse":4,"text":["> He asked You for life, and You granted it to him,","> Length of days for all time."]},{"verse":5,"text":["> His glory is great through Your salvation,","> Splendour and majesty You bestow upon him."]},{"verse":6,"text":["> For You make him exceedingly blessed forever;","> You fill him with joy in Your presence."]},{"verse":7,"text":["> For the king has faith in the Lord,","> And through the steadfastness of the Most High he will remain unshaken."]},{"text":["---"]},{"verse":8,"text":["> Your hand will reach all your enemies;","> Your right hand will seize those who bear hatred towards you."]},{"verse":9,"text":["> You will make them like a blazing furnace in the time of your anger;","> The Lord will consume them in His wrath,","> And fire will engulf them."]},{"verse":10,"text":["> You will remove their descendants from the earth,","> And their offspring from among the children of mankind."]},{"verse":11,"text":["> Though they plotted evil against You","> And devised a scheme,","> They will not prevail."]},{"verse":12,"text":["> For You will make them retreat;","> You will aim at their faces with Your bowstrings."]},{"text":["---"]},{"verse":13,"text":["> Be lifted high, Lord, in Your strength;","> We will sing and praise Your might."]}]}