{"book":"Psalm","chapter":33,"verses":[{"verse":1,"text":["> Rejoice in the Lord, you righteous;","> Praise is fitting for the upright."]},{"verse":2,"text":["> Offer thanks to the Lord with the lyre;","> Sing to Him with a harp of ten strings."]},{"verse":3,"text":["> Sing to Him a new song;","> Play skillfully with joyful shouts."]},{"text":["---"]},{"verse":4,"text":["> For the word of the Lord is true,","> And all His work is done with faithfulness."]},{"verse":5,"text":["> He cherishes righteousness and justice;","> The earth is filled with the goodness of the Lord."]},{"text":["---"]},{"verse":6,"text":["> By the word of the Lord the heavens were created,","> And by the breath of His mouth all their host."]},{"verse":7,"text":["> He gathers the waters of the sea as a heap;","> He stores the depths in storehouses."]},{"verse":8,"text":["> Let the whole earth revere the Lord;","> Let all the inhabitants of the world stand in awe of Him."]},{"verse":9,"text":["> For He spoke, and it came into existence;","> He gave the command, and it was established."]},{"text":["---"]},{"verse":10,"text":["> The Lord thwarts the counsel of nations;","> He frustrates the schemes of peoples."]},{"verse":11,"text":["> The counsel of the Lord endures forever,","> The thoughts of His heart through all generations."]},{"text":["---"]},{"verse":12,"text":["> Fortunate is the nation whose God is the Lord,","> The people He has chosen as His own possession."]},{"verse":13,"text":["> The Lord observes from heaven;","> He sees all the children of humanity;"]},{"verse":14,"text":["> From His dwelling place He watches","> All the inhabitants of the earth,"]},{"verse":15,"text":["> He who shapes the hearts of them all,","> He who comprehends all their deeds."]},{"text":["---"]},{"verse":16,"text":["> A king is not saved by a large army;","> A warrior is not delivered by great strength."]},{"verse":17,"text":["> A horse is a vain hope for victory;","> Nor does it deliver by its great strength."]},{"verse":18,"text":["> Behold, the eye of the Lord is on those who revere Him,","> On those who hope in His faithfulness,"]},{"verse":19,"text":["> To deliver their soul from death","> And to sustain them in famine."]},{"text":["---"]},{"verse":20,"text":["> Our soul awaits the Lord;","> He is our help and our shield."]},{"verse":21,"text":["> For our heart delights in Him,","> Because we trust in His holy name."]},{"verse":22,"text":["> Let Your favour, Lord, be upon us,","> Just as we have hoped in You."]}]}