{"book":"Psalm","chapter":84,"verses":[{"text":["For the music director; on the Gittith. A Psalm of the sons of Korah."]},{"verse":1,"text":["> How lovely are Your dwelling places,","> Lord of armies!"]},{"verse":2,"text":["> My soul longs and even yearns for the courtyards of the Lord;","> My heart and my flesh rejoice in the living God."]},{"verse":3,"text":["> The bird also finds a house,","> And the swallow a nest for herself, where she may place her young:","> Your altars, Lord of armies,","> My King and my God."]},{"verse":4,"text":["> Happy are those who reside in Your house!","> They continually praise You.","> Selah"]},{"text":["---"]},{"verse":5,"text":["> Fortunate is the person whose strength is in You,","> In whose heart are the paths to Zion!"]},{"verse":6,"text":["> As they pass through the Valley of Baca, they make it a place of springs;","> The early rain also covers it with blessings."]},{"verse":7,"text":["> They progress from strength to strength,","> Each one appears before God in Zion."]},{"text":["---"]},{"verse":8,"text":["> Lord God of armies, hear my prayer;","> Attend, God of Jacob!","> Selah"]},{"verse":9,"text":["> Behold our shield, God,","> And regard the face of Your anointed."]},{"text":["---"]},{"verse":10,"text":["> For a day in Your courtyards is more desirable than a thousand elsewhere.","> I would prefer to stand at the threshold of the house of my God","> Than to dwell in the tents of wickedness."]},{"verse":11,"text":["> For the Lord God is a sun and shield;","> The Lord bestows grace and honour;","> He withholds no good thing from those who walk with integrity."]},{"text":["---"]},{"verse":12,"text":["> Lord of armies,","> Fortunate is the person who places their trust in You!"]}]}