{"book":"Psalm","chapter":128,"verses":[{"text":["A Song of Ascents."]},{"verse":1,"text":["> Blessed is everyone who fears the Lord,","> Who walks in His ways."]},{"verse":2,"text":["> You will eat the fruit of the labour of your hands;","> You will be happy, and it will go well for you."]},{"verse":3,"text":["> Your wife will be like a fruitful vine within your home,","> Your children like young olive shoots around your table."]},{"verse":4,"text":["> Observe, for in this manner shall a man","> Who reveres the Lord be favoured."]},{"text":["---"]},{"verse":5,"text":["> May the Lord bless you from Zion,","> And may you witness the flourishing of Jerusalem all the days of your life."]},{"verse":6,"text":["> Truly, may you see your descendants.","> Peace be upon Israel!"]}]}