{"book":"2 Samuel","chapter":18,"verses":[{"verse":1,"text":["Então Davi reuniu o povo que estava com ele,","e colocou sobre eles comandantes de mil e comandantes de cem."]},{"verse":2,"text":["Davi enviou o exército: um terço sob o comando de Joabe,","um terço sob o comando de Abisai, filho de Zeruia, irmão de Joabe,","e um terço sob o comando de Itai, o geteu.","E o rei disse ao povo,","“Eu mesmo certamente sairei com vocês também.”"]},{"verse":3,"text":["Mas o povo disse,","“Você não deve sair. Pois se fugirmos, eles não se importarão conosco;","mesmo que metade de nós morra, eles não se importarão.","Mas você vale por dez mil de nós.","Portanto, é melhor que você esteja pronto para enviar ajuda da cidade.”"]},{"verse":4,"text":["O rei lhes disse,","“Farei o que parecer melhor aos seus olhos.”","Assim, o rei ficou ao lado do portão,","e todo o povo saiu por centenas e por milhares."]},{"verse":5,"text":["E o rei ordenou a Joabe, Abisai e Itai, dizendo,","“Tratem gentilmente, por minha causa, o jovem Absalão.”","E todo o povo ouviu o rei dar ordens a respeito de Absalão aos comandantes."]},{"text":["---"]},{"verse":6,"text":["Então o povo saiu ao campo para encontrar Israel,","e a batalha foi travada na floresta de Efraim."]},{"verse":7,"text":["Ali o povo de Israel foi derrotado pelos servos de Davi,","e a matança naquele dia foi grande—vinte mil homens."]},{"verse":8,"text":["A batalha se espalhou por todo o campo,","e a floresta devorou mais pessoas naquele dia do que a espada devorou."]},{"text":["---"]},{"verse":9,"text":["Agora Absalão encontrou os servos de Davi.","Absalão estava montado em sua mula,","e a mula passou por baixo dos ramos espessos de um grande carvalho.","Sua cabeça ficou presa na árvore,","e ele ficou pendurado entre o céu e a terra,","enquanto a mula que estava debaixo dele continuou."]},{"verse":10,"text":["Um certo homem viu isso e contou a Joabe,","“Eis que vi Absalão pendurado em um carvalho.”"]},{"verse":11,"text":["Então Joabe disse ao homem que lhe contou,","“Você o viu! Por que então não o feriu ali no chão?","Eu teria lhe dado dez peças de prata e um cinto.”"]},{"verse":12,"text":["Mas o homem disse a Joabe,","“Mesmo que eu recebesse mil peças de prata,","não estenderia minha mão contra o filho do rei;","pois em nossa audição o rei ordenou a você, Abisai e Itai, dizendo,","‘Protejam o jovem Absalão por minha causa.’"]},{"verse":13,"text":["Caso contrário, se eu tivesse agido traiçoeiramente contra sua vida,","e nada está oculto ao rei,","então você mesmo teria se afastado.”"]},{"verse":14,"text":["Então Joabe disse,","“Não perderei tempo com você.”","Assim, ele pegou três lanças em sua mão","e as enfiou no coração de Absalão enquanto ele ainda estava vivo no meio do carvalho."]},{"verse":15,"text":["E dez jovens que carregavam a armadura de Joabe cercaram Absalão","e o feriram e mataram."]},{"verse":16,"text":["Então Joabe tocou a trombeta,","e o povo voltou de perseguir Israel,","pois Joabe conteve as tropas."]},{"verse":17,"text":["Eles pegaram Absalão e o jogaram em uma grande cova na floresta,","e ergueram sobre ele um monte muito grande de pedras.","E todo Israel fugiu, cada um para sua tenda."]},{"verse":18,"text":["Agora Absalão, durante sua vida, tinha tomado e erguido para si um pilar,","que está no Vale do Rei,","pois ele disse, “Não tenho filho para preservar meu nome.”","E ele chamou o pilar com seu próprio nome,","e é chamado Monumento de Absalão até hoje."]},{"text":["---"]},{"verse":19,"text":["Então Aimaás, filho de Zadoque, disse,","“Deixe-me correr e levar a notícia ao rei,","que o Senhor o vingou, livrando-o da mão de seus inimigos.”"]},{"verse":20,"text":["Mas Joabe lhe disse,","“Você não levará notícias hoje, mas levará notícias outro dia.","Hoje você não entregará a notícia,","porque o filho do rei está morto.”"]},{"verse":21,"text":["Então Joabe disse a um cuxita,","“Vá, conte ao rei o que você viu.”","Assim, o cuxita se curvou a Joabe e correu."]},{"verse":22,"text":["Aimaás, filho de Zadoque, novamente disse a Joabe,","“Seja o que for que aconteça, por favor, deixe-me também correr atrás do cuxita.”","E Joabe disse, “Por que você correria, meu filho, vendo que não tem recompensa pela notícia?”"]},{"verse":23,"text":["“Mas seja o que for que aconteça,” ele disse, “eu correrei.”","Então ele lhe disse, “Corra.”","Então Aimaás correu pelo caminho da planície e ultrapassou o cuxita."]},{"text":["---"]},{"verse":24,"text":["Agora Davi estava sentado entre os dois portões,","e o vigia subiu ao telhado do portão junto ao muro,","e levantou os olhos e olhou, e eis que um homem estava correndo sozinho."]},{"verse":25,"text":["O vigia chamou e contou ao rei.","E o rei disse, “Se ele está sozinho, há boas notícias em sua boca.”","E ele se aproximou cada vez mais."]},{"verse":26,"text":["Então o vigia viu outro homem correndo,","e o vigia chamou ao porteiro e disse,","“Eis que outro homem está correndo sozinho.”","E o rei disse, “Ele também está trazendo boas notícias.”"]},{"verse":27,"text":["O vigia disse,","“Acho que a corrida do primeiro é como a corrida de Aimaás, filho de Zadoque.”","E o rei disse, “Ele é um bom homem, e vem com boas notícias.”"]},{"verse":28,"text":["Então Aimaás gritou e disse ao rei,","“Tudo está bem.”","E ele se prostrou diante do rei com o rosto em terra e disse,","“Bendito seja o Senhor, seu Deus,","que entregou os homens que levantaram a mão contra meu senhor, o rei.”"]},{"verse":29,"text":["O rei disse,","“Está bem com o jovem Absalão?”","E Aimaás respondeu,","“Quando Joabe enviou o servo do rei, seu servo, eu vi uma grande comoção,","mas não sabia o que era.”"]},{"verse":30,"text":["O rei lhe instruiu, “Afaste-se e espere aqui.”","Então ele se afastou e esperou."]},{"verse":31,"text":["Então eis que o cuxita chegou e disse,","“Que meu senhor, o rei, receba boas notícias,","pois o Senhor o vingou neste dia","livrando-o da mão de todos os que se levantaram contra você.”"]},{"verse":32,"text":["E o rei disse ao cuxita,","“Está bem com o jovem Absalão?”","E o cuxita respondeu,","“Que os inimigos de meu senhor, o rei, e todos os que se levantam contra você para o mal,","sejam como aquele jovem.”"]},{"text":["---"]},{"verse":33,"text":["Então o rei ficou profundamente abalado,","e subiu à câmara sobre o portão e chorou.","Enquanto subia, ele disse,","“Oh meu filho Absalão, meu filho, meu filho Absalão!","Quem me dera ter morrido em seu lugar,","Oh Absalão, meu filho, meu filho!”"]}]}