{"book":"Job","chapter":4,"verses":[{"verse":1,"text":["Eliphaz the Temanite responded:"]},{"verse":2,"text":["> “If one dares to speak with you, will you become restless?","> Yet who can hold back words?"]},{"verse":3,"text":["> Consider how you have taught many,","> and how you have strengthened weak hands."]},{"verse":4,"text":["> Your words have supported those who were stumbling,","> and you have strengthened faltering knees."]},{"verse":5,"text":["> But now it comes upon you, and you are disheartened;","> it touches you, and you are alarmed."]},{"verse":6,"text":["> Is not your reverence for God your confidence,","> and the integrity of your ways your hope?"]},{"text":["---"]},{"verse":7,"text":["> “Reflect now, who ever perished being innocent?","> Or where have the upright been destroyed?"]},{"verse":8,"text":["> As I have observed,","> those who plough iniquity","> and those who sow trouble reap the same."]},{"verse":9,"text":["> By the breath of God they perish;","> by the blast of His anger they are consumed."]},{"verse":10,"text":["> The roaring of the lion and the voice of the fierce lion,","> yet the teeth of the young lions are shattered."]},{"verse":11,"text":["> The lion perishes for lack of prey,","> and the cubs of the lioness are dispersed."]},{"verse":12,"text":["> “A word was secretly brought to me,","> and my ear caught a whisper of it."]},{"verse":13,"text":["> Amid troubling thoughts from visions of the night,","> when deep sleep falls on people,"]},{"verse":14,"text":["> fear and trembling came upon me,","> and made all my bones shake."]},{"verse":15,"text":["> A spirit glided past my face;","> the hair of my flesh stood on end."]},{"verse":16,"text":["> It stood still, but I could not discern its form;","> a shape was before my eyes,","> and I heard a quiet voice:"]},{"verse":17,"text":["> ‘Can a mortal be just before God?","> Can a man be pure before his Maker?"]},{"verse":18,"text":["> He puts no trust even in His servants,","> and He charges His angels with error."]},{"verse":19,"text":["> How much more those who dwell in houses of clay,","> whose foundation is in the dust,","> who are crushed more easily than a moth!"]},{"verse":20,"text":["> From morning to evening they are shattered;","> unnoticed, they perish forever."]},{"verse":21,"text":["> Are not the cords of their tent pulled up within them?","> They die without wisdom.’"]}]}