{"book":"Salmos","chapter":3,"verses":[{"text":["Um Salmo de Davi, quando ele fugiu de seu filho Absalão."]},{"verse":1,"text":["> Senhor, como aumentaram os meus inimigos!","> Muitos se levantam contra mim."]},{"verse":2,"text":["> Muitos dizem a meu respeito,","> “Não há salvação para ele em Deus.”","> Selá"]},{"text":["---"]},{"verse":3,"text":["> Mas Tu, Senhor, és um escudo ao meu redor,","> Minha glória, e o que exalta a minha cabeça."]},{"verse":4,"text":["> Com a minha voz clamei ao Senhor,","> E Ele me respondeu do Seu santo monte.","> Selá"]},{"text":["---"]},{"verse":5,"text":["> Eu me deitei e dormi;","> Acordei, pois o Senhor me sustenta."]},{"verse":6,"text":["> Não temerei os milhares de pessoas","> Que se puseram contra mim ao meu redor."]},{"text":["---"]},{"verse":7,"text":["> Levanta-te, Senhor; salva-me, meu Deus!","> Pois feriste todos os meus inimigos no queixo;","> Quebraste os dentes dos ímpios."]},{"text":["---"]},{"verse":8,"text":["> A salvação vem do Senhor;","> Sobre o Teu povo seja a Tua bênção.","> Selá"]}]}