{"book":"Salmos","chapter":11,"verses":[{"text":["Para o diretor de música. Um Salmo de Davi."]},{"verse":1,"text":["> No Senhor eu me refugio;","> Como vocês podem dizer à minha alma,","> “Fuja como um pássaro para o seu monte;"]},{"verse":2,"text":["> Pois, vejam, os ímpios preparam o arco,","> Eles preparam a flecha na corda","> Para atirar nas sombras contra os retos de coração."]},{"verse":3,"text":["> Se os próprios fundamentos forem destruídos,","> Que ação pode o justo tomar?”"]},{"text":["---"]},{"verse":4,"text":["> O Senhor está em Seu santo templo;","> O trono do Senhor está nos céus;","> Seus olhos observam, Suas pálpebras testam os filhos da humanidade."]},{"verse":5,"text":["> O Senhor examina tanto os justos quanto os ímpios,","> E Ele detesta profundamente aquele que se deleita na violência."]},{"verse":6,"text":["> Ele fará chover brasas de fogo sobre os ímpios,","> Fogo e enxofre e vento ardente serão a porção do seu cálice."]},{"text":["---"]},{"verse":7,"text":["> Pois o Senhor é justo, Ele aprecia a retidão;","> Aqueles que são retos contemplarão Sua face."]}]}