{"book":"Salmos","chapter":124,"verses":[{"text":["Cântico de Peregrinação. De Davi."]},{"verse":1,"text":["> “Se não fosse o Senhor que esteve ao nosso lado,”","> Diga agora Israel,"]},{"verse":2,"text":["> “Se o Senhor não tivesse estado ao nosso lado","> Quando as pessoas se levantaram contra nós,"]},{"verse":3,"text":["> Então nos teriam devorado completamente,","> Quando sua ira ardia ferozmente contra nós;"]},{"verse":4,"text":["> Então as águas teriam nos inundado,","> A corrente teria passado sobre a nossa alma;"]},{"verse":5,"text":["> e as águas impetuosas teriam passado sobre a nossa alma.”"]},{"text":["---"]},{"verse":6,"text":["> Bendito seja o Senhor,","> Que não nos permitiu ser dilacerados por seus dentes."]},{"verse":7,"text":["> Nossa alma escapou como um pássaro do laço do caçador;","> O laço quebrou-se, e nós escapamos."]},{"verse":8,"text":["> Nosso auxílio está no nome do Senhor,","> Que fez o céu e a terra."]}]}